{"d" : [{"__metadata": {"uri": "http://datamall.mytransport.sg/LTAoDataService.svc/SBSTRouteSet(153293020)", "type": "LTAModel.SBSTRoute"}, "SBSTRouteID": 153293020, "SR_SVC_NUM": "76", "SR_SVC_DIR": "1", "SR_ROUT_SEQ": "10", "SR_BS_CODE": "54241", "SR_EXP_CODE": "", "SR_DISTANCE": "3.4", "SR_FST_WD": "0548", "SR_LST_WD": "2220", "SR_FST_SAT": "0545", "SR_LST_SAT": "2221", "SR_FST_SUN": "0600", "SR_LST_SUN": "2225", "Summary": "SR_SVC_NUM: 76 SR_SVC_DIR: 1 SR_BS_CODE: 54241 ", "CreateDate": "\/Date(1428320010767)\/"}, {"__metadata": {"uri": "http://datamall.mytransport.sg/LTAoDataService.svc/SBSTRouteSet(153293021)", "type": "LTAModel.SBSTRoute"}, "SBSTRouteID": 153293021, "SR_SVC_NUM": "76", "SR_SVC_DIR": "1", "SR_ROUT_SEQ": "11", "SR_BS_CODE": "54261", "SR_EXP_CODE": "", "SR_DISTANCE": "3.9", "SR_FST_WD": "0551", "SR_LST_WD": "2223", "SR_FST_SAT": "0547", "SR_LST_SAT": "2223", "SR_FST_SUN": "0602", "SR_LST_SUN": "2227", "Summary": "SR_SVC_NUM: 76 SR_SVC_DIR: 1 SR_BS_CODE: 54261 ", "CreateDate": "\/Date(1428320010770)\/"}, {"__metadata": {"uri": "http://datamall.mytransport.sg/LTAoDataService.svc/SBSTRouteSet(153293022)", "type": "LTAModel.SBSTRoute"}, "SBSTRouteID": 153293022, "SR_SVC_NUM": "76", "SR_SVC_DIR": "1", "SR_ROUT_SEQ": "12", "SR_BS_CODE": "54271", "SR_EXP_CODE": "", "SR_DISTANCE": "4.2", "SR_FST_WD": "0552", "SR_LST_WD": "2224", "SR_FST_SAT": "0548", "SR_LST_SAT": "2224", "SR_FST_SUN": "0603", "SR_LST_SUN": "2228", "Summary": "SR_SVC_NUM: 76 SR_SVC_DIR: 1 SR_BS_CODE: 54271 ", "CreateDate": "\/Date(1428320010777)\/"}, {"__metadata": {"uri": "http://datamall.mytransport.sg/LTAoDataService.svc/SBSTRouteSet(153293023)", "type": "LTAModel.SBSTRoute"}, "SBSTRouteID": 153293023, "SR_SVC_NUM": "76", "SR_SVC_DIR": "1", "SR_ROUT_SEQ": "13", "SR_BS_CODE": "54281", "SR_EXP_CODE": "", "SR_DISTANCE": "4.5", "SR_FST_WD": "0553", "SR_LST_WD": "2225", "SR_FST_SAT": "0549", "SR_LST_SAT": "2225", "SR_FST_SUN": "0604", "SR_LST_SUN": "2229", "Summary": "SR_SVC_NUM: 76 SR_SVC_DIR: 1 SR_BS_CODE: 54281 ", "CreateDate": "\/Date(1428320010783)\/"}, {"__metadata": {"uri": "http://datamall.mytransport.sg/LTAoDataService.svc/SBSTRouteSet(153293024)", "type": "LTAModel.SBSTRoute"}, "SBSTRouteID": 153293024, "SR_SVC_NUM": "76", "SR_SVC_DIR": "1", "SR_ROUT_SEQ": "14", "SR_BS_CODE": "54291", "SR_EXP_CODE": "", "SR_DISTANCE": "4.8", "SR_FST_WD": "0554", "SR_LST_WD": "2226", "SR_FST_SAT": "0550", "SR_LST_SAT": "2226", "SR_FST_SUN": "0605", "SR_LST_SUN": "2230", "Summary": "SR_SVC_NUM: 76 SR_SVC_DIR: 1 SR_BS_CODE: 54291 ", "CreateDate": "\/Date(1428320010790)\/"}, {"__metadata": {"uri": "http://datamall.mytransport.sg/LTAoDataService.svc/SBSTRouteSet(153293025)", "type": "LTAModel.SBSTRoute"}, "SBSTRouteID": 153293025, "SR_SVC_NUM": "76", "SR_SVC_DIR": "1", "SR_ROUT_SEQ": "15", "SR_BS_CODE": "54301", "SR_EXP_CODE": "", "SR_DISTANCE": "5.3", "SR_FST_WD": "0556", "SR_LST_WD": "2228", "SR_FST_SAT": "0551", "SR_LST_SAT": "2228", "SR_FST_SUN": "0607", "SR_LST_SUN": "2232", "Summary": "SR_SVC_NUM: 76 SR_SVC_DIR: 1 SR_BS_CODE: 54301 ", "CreateDate": "\/Date(1428320010793)\/"}, {"__metadata": {"uri": "http://datamall.mytransport.sg/LTAoDataService.svc/SBSTRouteSet(153293026)", "type": "LTAModel.SBSTRoute"}, "SBSTRouteID": 153293026, "SR_SVC_NUM": "76", "SR_SVC_DIR": "1", "SR_ROUT_SEQ": "16", "SR_BS_CODE": "66341", "SR_EXP_CODE": "", "SR_DISTANCE": "5.6", "SR_FST_WD": "0557", "SR_LST_WD": "2229", "SR_FST_SAT": "0552", "SR_LST_SAT": "2229", "SR_FST_SUN": "0608", "SR_LST_SUN": "2233", "Summary": "SR_SVC_NUM: 76 SR_SVC_DIR: 1 SR_BS_CODE: 66341 ", "CreateDate": "\/Date(1428320010800)\/"}, {"__metadata": {"uri": "http://datamall.mytransport.sg/LTAoDataService.svc/SBSTRouteSet(153293027)", "type": "LTAModel.SBSTRoute"}, "SBSTRouteID": 153293027, "SR_SVC_NUM": "76", "SR_SVC_DIR": "1", "SR_ROUT_SEQ": "17", "SR_BS_CODE": "66331", "SR_EXP_CODE": "", "SR_DISTANCE": "6.2", "SR_FST_WD": "0559", "SR_LST_WD": "2231", "SR_FST_SAT": "0554", "SR_LST_SAT": "2231", "SR_FST_SUN": "0610", "SR_LST_SUN": "2235", "Summary": "SR_SVC_NUM: 76 SR_SVC_DIR: 1 SR_BS_CODE: 66331 ", "CreateDate": "\/Date(1428320010803)\/"}, {"__metadata": {"uri": "http://datamall.mytransport.sg/LTAoDataService.svc/SBSTRouteSet(153293028)", "type": "LTAModel.SBSTRoute"}, "SBSTRouteID": 153293028, "SR_SVC_NUM": "76", "SR_SVC_DIR": "1", "SR_ROUT_SEQ": "18", "SR_BS_CODE": "66101", "SR_EXP_CODE": "", "SR_DISTANCE": "6.6", "SR_FST_WD": "0600", "SR_LST_WD": "2232", "SR_FST_SAT": "0555", "SR_LST_SAT": "2232", "SR_FST_SUN": "0611", "SR_LST_SUN": "2236", "Summary": "SR_SVC_NUM: 76 SR_SVC_DIR: 1 SR_BS_CODE: 66101 ", "CreateDate": "\/Date(1428320010810)\/"}, {"__metadata": {"uri": "http://datamall.mytransport.sg/LTAoDataService.svc/SBSTRouteSet(153293029)", "type": "LTAModel.SBSTRoute"}, "SBSTRouteID": 153293029, "SR_SVC_NUM": "76", "SR_SVC_DIR": "1", "SR_ROUT_SEQ": "19", "SR_BS_CODE": "63219", "SR_EXP_CODE": "", "SR_DISTANCE": "7.1", "SR_FST_WD": "0602", "SR_LST_WD": "2234", "SR_FST_SAT": "0556", "SR_LST_SAT": "2233", "SR_FST_SUN": "0612", "SR_LST_SUN": "2237", "Summary": "SR_SVC_NUM: 76 SR_SVC_DIR: 1 SR_BS_CODE: 63219 ", "CreateDate": "\/Date(1428320010817)\/"}, {"__metadata": {"uri": "http://datamall.mytransport.sg/LTAoDataService.svc/SBSTRouteSet(153293030)", "type": "LTAModel.SBSTRoute"}, "SBSTRouteID": 153293030, "SR_SVC_NUM": "76", "SR_SVC_DIR": "1", "SR_ROUT_SEQ": "20", "SR_BS_CODE": "63209", "SR_EXP_CODE": "", "SR_DISTANCE": "7.4", "SR_FST_WD": "0603", "SR_LST_WD": "2235", "SR_FST_SAT": "0557", "SR_LST_SAT": "2234", "SR_FST_SUN": "0613", "SR_LST_SUN": "2238", "Summary": "SR_SVC_NUM: 76 SR_SVC_DIR: 1 SR_BS_CODE: 63209 ", "CreateDate": "\/Date(1428320010823)\/"}, {"__metadata": {"uri": "http://datamall.mytransport.sg/LTAoDataService.svc/SBSTRouteSet(153293031)", "type": "LTAModel.SBSTRoute"}, "SBSTRouteID": 153293031, "SR_SVC_NUM": "76", "SR_SVC_DIR": "1", "SR_ROUT_SEQ": "21", "SR_BS_CODE": "63199", "SR_EXP_CODE": "", "SR_DISTANCE": "7.8", "SR_FST_WD": "0604", "SR_LST_WD": "2236", "SR_FST_SAT": "0558", "SR_LST_SAT": "2236", "SR_FST_SUN": "0615", "SR_LST_SUN": "2240", "Summary": "SR_SVC_NUM: 76 SR_SVC_DIR: 1 SR_BS_CODE: 63199 ", "CreateDate": "\/Date(1428320010830)\/"}, {"__metadata": {"uri": "http://datamall.mytransport.sg/LTAoDataService.svc/SBSTRouteSet(153293032)", "type": "LTAModel.SBSTRoute"}, "SBSTRouteID": 153293032, "SR_SVC_NUM": "76", "SR_SVC_DIR": "1", "SR_ROUT_SEQ": "22", "SR_BS_CODE": "63189", "SR_EXP_CODE": "", "SR_DISTANCE": "8.1", "SR_FST_WD": "0605", "SR_LST_WD": "2237", "SR_FST_SAT": "0559", "SR_LST_SAT": "2237", "SR_FST_SUN": "0616", "SR_LST_SUN": "2241", "Summary": "SR_SVC_NUM: 76 SR_SVC_DIR: 1 SR_BS_CODE: 63189 ", "CreateDate": "\/Date(1428320010837)\/"}, {"__metadata": {"uri": "http://datamall.mytransport.sg/LTAoDataService.svc/SBSTRouteSet(153293033)", "type": "LTAModel.SBSTRoute"}, "SBSTRouteID": 153293033, "SR_SVC_NUM": "76", "SR_SVC_DIR": "1", "SR_ROUT_SEQ": "23", "SR_BS_CODE": "63179", "SR_EXP_CODE": "", "SR_DISTANCE": "8.3", "SR_FST_WD": "0606", "SR_LST_WD": "2238", "SR_FST_SAT": "0559", "SR_LST_SAT": "2237", "SR_FST_SUN": "0616", "SR_LST_SUN": "2241", "Summary": "SR_SVC_NUM: 76 SR_SVC_DIR: 1 SR_BS_CODE: 63179 ", "CreateDate": "\/Date(1428320010843)\/"}, {"__metadata": {"uri": "http://datamall.mytransport.sg/LTAoDataService.svc/SBSTRouteSet(153293034)", "type": "LTAModel.SBSTRoute"}, "SBSTRouteID": 153293034, "SR_SVC_NUM": "76", "SR_SVC_DIR": "1", "SR_ROUT_SEQ": "24", "SR_BS_CODE": "63369", "SR_EXP_CODE": "", "SR_DISTANCE": "8.7", "SR_FST_WD": "0607", "SR_LST_WD": "2239", "SR_FST_SAT": "0601", "SR_LST_SAT": "2238", "SR_FST_SUN": "0617", "SR_LST_SUN": "2242", "Summary": "SR_SVC_NUM: 76 SR_SVC_DIR: 1 SR_BS_CODE: 63369 ", "CreateDate": "\/Date(1428320010850)\/"}, {"__metadata": {"uri": "http://datamall.mytransport.sg/LTAoDataService.svc/SBSTRouteSet(153293035)", "type": "LTAModel.SBSTRoute"}, "SBSTRouteID": 153293035, "SR_SVC_NUM": "76", "SR_SVC_DIR": "1", "SR_ROUT_SEQ": "25", "SR_BS_CODE": "63149", "SR_EXP_CODE": "", "SR_DISTANCE": "8.9", "SR_FST_WD": "0608", "SR_LST_WD": "2240", "SR_FST_SAT": "0601", "SR_LST_SAT": "2239", "SR_FST_SUN": "0618", "SR_LST_SUN": "2243", "Summary": "SR_SVC_NUM: 76 SR_SVC_DIR: 1 SR_BS_CODE: 63149 ", "CreateDate": "\/Date(1428320010853)\/"}, {"__metadata": {"uri": "http://datamall.mytransport.sg/LTAoDataService.svc/SBSTRouteSet(153293036)", "type": "LTAModel.SBSTRoute"}, "SBSTRouteID": 153293036, "SR_SVC_NUM": "76", "SR_SVC_DIR": "1", "SR_ROUT_SEQ": "26", "SR_BS_CODE": "62059", "SR_EXP_CODE": "", "SR_DISTANCE": "9.5", "SR_FST_WD": "0610", "SR_LST_WD": "2242", "SR_FST_SAT": "0603", "SR_LST_SAT": "2241", "SR_FST_SUN": "0620", "SR_LST_SUN": "2245", "Summary": "SR_SVC_NUM: 76 SR_SVC_DIR: 1 SR_BS_CODE: 62059 ", "CreateDate": "\/Date(1428320010860)\/"}, {"__metadata": {"uri": "http://datamall.mytransport.sg/LTAoDataService.svc/SBSTRouteSet(153293037)", "type": "LTAModel.SBSTRoute"}, "SBSTRouteID": 153293037, "SR_SVC_NUM": "76", "SR_SVC_DIR": "1", "SR_ROUT_SEQ": "27", "SR_BS_CODE": "62049", "SR_EXP_CODE": "", "SR_DISTANCE": "9.9", "SR_FST_WD": "0611", "SR_LST_WD": "2243", "SR_FST_SAT": "0604", "SR_LST_SAT": "2242", "SR_FST_SUN": "0621", "SR_LST_SUN": "2246", "Summary": "SR_SVC_NUM: 76 SR_SVC_DIR: 1 SR_BS_CODE: 62049 ", "CreateDate": "\/Date(1428320010867)\/"}, {"__metadata": {"uri": "http://datamall.mytransport.sg/LTAoDataService.svc/SBSTRouteSet(153293038)", "type": "LTAModel.SBSTRoute"}, "SBSTRouteID": 153293038, "SR_SVC_NUM": "76", "SR_SVC_DIR": "1", "SR_ROUT_SEQ": "28", "SR_BS_CODE": "62039", "SR_EXP_CODE": "", "SR_DISTANCE": "10.2", "SR_FST_WD": "0613", "SR_LST_WD": "2244", "SR_FST_SAT": "0605", "SR_LST_SAT": "2243", "SR_FST_SUN": "0622", "SR_LST_SUN": "2247", "Summary": "SR_SVC_NUM: 76 SR_SVC_DIR: 1 SR_BS_CODE: 62039 ", "CreateDate": "\/Date(1428320010873)\/"}, {"__metadata": {"uri": "http://datamall.mytransport.sg/LTAoDataService.svc/SBSTRouteSet(153293039)", "type": "LTAModel.SBSTRoute"}, "SBSTRouteID": 153293039, "SR_SVC_NUM": "76", "SR_SVC_DIR": "1", "SR_ROUT_SEQ": "29", "SR_BS_CODE": "62029", "SR_EXP_CODE": "", "SR_DISTANCE": "10.5", "SR_FST_WD": "0614", "SR_LST_WD": "2246", "SR_FST_SAT": "0606", "SR_LST_SAT": "2244", "SR_FST_SUN": "0623", "SR_LST_SUN": "2248", "Summary": "SR_SVC_NUM: 76 SR_SVC_DIR: 1 SR_BS_CODE: 62029 ", "CreateDate": "\/Date(1428320010880)\/"}, {"__metadata": {"uri": "http://datamall.mytransport.sg/LTAoDataService.svc/SBSTRouteSet(153293040)", "type": "LTAModel.SBSTRoute"}, "SBSTRouteID": 153293040, "SR_SVC_NUM": "76", "SR_SVC_DIR": "1", "SR_ROUT_SEQ": "30", "SR_BS_CODE": "62019", "SR_EXP_CODE": "", "SR_DISTANCE": "10.7", "SR_FST_WD": "0615", "SR_LST_WD": "2246", "SR_FST_SAT": "0607", "SR_LST_SAT": "2245", "SR_FST_SUN": "0624", "SR_LST_SUN": "2249", "Summary": "SR_SVC_NUM: 76 SR_SVC_DIR: 1 SR_BS_CODE: 62019 ", "CreateDate": "\/Date(1428320010883)\/"}, {"__metadata": {"uri": "http://datamall.mytransport.sg/LTAoDataService.svc/SBSTRouteSet(153293041)", "type": "LTAModel.SBSTRoute"}, "SBSTRouteID": 153293041, "SR_SVC_NUM": "76", "SR_SVC_DIR": "1", "SR_ROUT_SEQ": "31", "SR_BS_CODE": "70309", "SR_EXP_CODE": "", "SR_DISTANCE": "11.0", "SR_FST_WD": "0616", "SR_LST_WD": "2248", "SR_FST_SAT": "0608", "SR_LST_SAT": "2246", "SR_FST_SUN": "0625", "SR_LST_SUN": "2250", "Summary": "SR_SVC_NUM: 76 SR_SVC_DIR: 1 SR_BS_CODE: 70309 ", "CreateDate": "\/Date(1428320010890)\/"}, {"__metadata": {"uri": "http://datamall.mytransport.sg/LTAoDataService.svc/SBSTRouteSet(153293042)", "type": "LTAModel.SBSTRoute"}, "SBSTRouteID": 153293042, "SR_SVC_NUM": "76", "SR_SVC_DIR": "1", "SR_ROUT_SEQ": "32", "SR_BS_CODE": "70299", "SR_EXP_CODE": "", "SR_DISTANCE": "11.2", "SR_FST_WD": "0617", "SR_LST_WD": "2249", "SR_FST_SAT": "0609", "SR_LST_SAT": "2247", "SR_FST_SUN": "0626", "SR_LST_SUN": "2251", "Summary": "SR_SVC_NUM: 76 SR_SVC_DIR: 1 SR_BS_CODE: 70299 ", "CreateDate": "\/Date(1428320010897)\/"}, {"__metadata": {"uri": "http://datamall.mytransport.sg/LTAoDataService.svc/SBSTRouteSet(153293043)", "type": "LTAModel.SBSTRoute"}, "SBSTRouteID": 153293043, "SR_SVC_NUM": "76", "SR_SVC_DIR": "1", "SR_ROUT_SEQ": "33", "SR_BS_CODE": "70289", "SR_EXP_CODE": "", "SR_DISTANCE": "11.5", "SR_FST_WD": "0618", "SR_LST_WD": "2250", "SR_FST_SAT": "0610", "SR_LST_SAT": "2248", "SR_FST_SUN": "0627", "SR_LST_SUN": "2252", "Summary": "SR_SVC_NUM: 76 SR_SVC_DIR: 1 SR_BS_CODE: 70289 ", "CreateDate": "\/Date(1428320010900)\/"}, {"__metadata": {"uri": "http://datamall.mytransport.sg/LTAoDataService.svc/SBSTRouteSet(153293044)", "type": "LTAModel.SBSTRoute"}, "SBSTRouteID": 153293044, "SR_SVC_NUM": "76", "SR_SVC_DIR": "1", "SR_ROUT_SEQ": "34", "SR_BS_CODE": "70279", "SR_EXP_CODE": "", "SR_DISTANCE": "12.0", "SR_FST_WD": "0620", "SR_LST_WD": "2251", "SR_FST_SAT": "0612", "SR_LST_SAT": "2250", "SR_FST_SUN": "0629", "SR_LST_SUN": "2254", "Summary": "SR_SVC_NUM: 76 SR_SVC_DIR: 1 SR_BS_CODE: 70279 ", "CreateDate": "\/Date(1428320010910)\/"}, {"__metadata": {"uri": "http://datamall.mytransport.sg/LTAoDataService.svc/SBSTRouteSet(153293045)", "type": "LTAModel.SBSTRoute"}, "SBSTRouteID": 153293045, "SR_SVC_NUM": "76", "SR_SVC_DIR": "1", "SR_ROUT_SEQ": "35", "SR_BS_CODE": "70269", "SR_EXP_CODE": "", "SR_DISTANCE": "12.3", "SR_FST_WD": "0621", "SR_LST_WD": "2252", "SR_FST_SAT": "0613", "SR_LST_SAT": "2251", "SR_FST_SUN": "0630", "SR_LST_SUN": "2255", "Summary": "SR_SVC_NUM: 76 SR_SVC_DIR: 1 SR_BS_CODE: 70269 ", "CreateDate": "\/Date(1428320010930)\/"}, {"__metadata": {"uri": "http://datamall.mytransport.sg/LTAoDataService.svc/SBSTRouteSet(153293046)", "type": "LTAModel.SBSTRoute"}, "SBSTRouteID": 153293046, "SR_SVC_NUM": "76", "SR_SVC_DIR": "1", "SR_ROUT_SEQ": "36", "SR_BS_CODE": "70259", "SR_EXP_CODE": "", "SR_DISTANCE": "12.8", "SR_FST_WD": "0623", "SR_LST_WD": "2254", "SR_FST_SAT": "0615", "SR_LST_SAT": "2253", "SR_FST_SUN": "0632", "SR_LST_SUN": "2257", "Summary": "SR_SVC_NUM: 76 SR_SVC_DIR: 1 SR_BS_CODE: 70259 ", "CreateDate": "\/Date(1428320010937)\/"}, {"__metadata": {"uri": "http://datamall.mytransport.sg/LTAoDataService.svc/SBSTRouteSet(153293047)", "type": "LTAModel.SBSTRoute"}, "SBSTRouteID": 153293047, "SR_SVC_NUM": "76", "SR_SVC_DIR": "1", "SR_ROUT_SEQ": "37", "SR_BS_CODE": "81101", "SR_EXP_CODE": "", "SR_DISTANCE": "13.2", "SR_FST_WD": "0625", "SR_LST_WD": "2256", "SR_FST_SAT": "0616", "SR_LST_SAT": "2254", "SR_FST_SUN": "0633", "SR_LST_SUN": "2258", "Summary": "SR_SVC_NUM: 76 SR_SVC_DIR: 1 SR_BS_CODE: 81101 ", "CreateDate": "\/Date(1428320010943)\/"}, {"__metadata": {"uri": "http://datamall.mytransport.sg/LTAoDataService.svc/SBSTRouteSet(153293048)", "type": "LTAModel.SBSTRoute"}, "SBSTRouteID": 153293048, "SR_SVC_NUM": "76", "SR_SVC_DIR": "1", "SR_ROUT_SEQ": "38", "SR_BS_CODE": "81111", "SR_EXP_CODE": "", "SR_DISTANCE": "13.5", "SR_FST_WD": "0626", "SR_LST_WD": "2257", "SR_FST_SAT": "0617", "SR_LST_SAT": "2255", "SR_FST_SUN": "0634", "SR_LST_SUN": "2259", "Summary": "SR_SVC_NUM: 76 SR_SVC_DIR: 1 SR_BS_CODE: 81111 ", "CreateDate": "\/Date(1428320010950)\/"}, {"__metadata": {"uri": "http://datamall.mytransport.sg/LTAoDataService.svc/SBSTRouteSet(153293049)", "type": "LTAModel.SBSTRoute"}, "SBSTRouteID": 153293049, "SR_SVC_NUM": "76", "SR_SVC_DIR": "1", "SR_ROUT_SEQ": "39", "SR_BS_CODE": "82119", "SR_EXP_CODE": "", "SR_DISTANCE": "13.9", "SR_FST_WD": "0628", "SR_LST_WD": "2258", "SR_FST_SAT": "0618", "SR_LST_SAT": "2257", "SR_FST_SUN": "0635", "SR_LST_SUN": "2301", "Summary": "SR_SVC_NUM: 76 SR_SVC_DIR: 1 SR_BS_CODE: 82119 ", "CreateDate": "\/Date(1428320010953)\/"}, {"__metadata": {"uri": "http://datamall.mytransport.sg/LTAoDataService.svc/SBSTRouteSet(153293050)", "type": "LTAModel.SBSTRoute"}, "SBSTRouteID": 153293050, "SR_SVC_NUM": "76", "SR_SVC_DIR": "1", "SR_ROUT_SEQ": "40", "SR_BS_CODE": "82099", "SR_EXP_CODE": "", "SR_DISTANCE": "14.3", "SR_FST_WD": "0629", "SR_LST_WD": "2300", "SR_FST_SAT": "0620", "SR_LST_SAT": "2258", "SR_FST_SUN": "0636", "SR_LST_SUN": "2302", "Summary": "SR_SVC_NUM: 76 SR_SVC_DIR: 1 SR_BS_CODE: 82099 ", "CreateDate": "\/Date(1428320010980)\/"}, {"__metadata": {"uri": "http://datamall.mytransport.sg/LTAoDataService.svc/SBSTRouteSet(153293051)", "type": "LTAModel.SBSTRoute"}, "SBSTRouteID": 153293051, "SR_SVC_NUM": "76", "SR_SVC_DIR": "1", "SR_ROUT_SEQ": "41", "SR_BS_CODE": "82089", "SR_EXP_CODE": "", "SR_DISTANCE": "14.5", "SR_FST_WD": "0630", "SR_LST_WD": "2300", "SR_FST_SAT": "0620", "SR_LST_SAT": "2259", "SR_FST_SUN": "0637", "SR_LST_SUN": "2303", "Summary": "SR_SVC_NUM: 76 SR_SVC_DIR: 1 SR_BS_CODE: 82089 ", "CreateDate": "\/Date(1428320010987)\/"}, {"__metadata": {"uri": "http://datamall.mytransport.sg/LTAoDataService.svc/SBSTRouteSet(153293052)", "type": "LTAModel.SBSTRoute"}, "SBSTRouteID": 153293052, "SR_SVC_NUM": "76", "SR_SVC_DIR": "1", "SR_ROUT_SEQ": "42", "SR_BS_CODE": "82079", "SR_EXP_CODE": "", "SR_DISTANCE": "14.8", "SR_FST_WD": "0631", "SR_LST_WD": "2302", "SR_FST_SAT": "0622", "SR_LST_SAT": "2300", "SR_FST_SUN": "0638", "SR_LST_SUN": "2304", "Summary": "SR_SVC_NUM: 76 SR_SVC_DIR: 1 SR_BS_CODE: 82079 ", "CreateDate": "\/Date(1428320011007)\/"}, {"__metadata": {"uri": "http://datamall.mytransport.sg/LTAoDataService.svc/SBSTRouteSet(153293053)", "type": "LTAModel.SBSTRoute"}, "SBSTRouteID": 153293053, "SR_SVC_NUM": "76", "SR_SVC_DIR": "1", "SR_ROUT_SEQ": "43", "SR_BS_CODE": "92169", "SR_EXP_CODE": "", "SR_DISTANCE": "15.2", "SR_FST_WD": "0633", "SR_LST_WD": "2303", "SR_FST_SAT": "0623", "SR_LST_SAT": "2301", "SR_FST_SUN": "0639", "SR_LST_SUN": "2305", "Summary": "SR_SVC_NUM: 76 SR_SVC_DIR: 1 SR_BS_CODE: 92169 ", "CreateDate": "\/Date(1428320011013)\/"}, {"__metadata": {"uri": "http://datamall.mytransport.sg/LTAoDataService.svc/SBSTRouteSet(153293054)", "type": "LTAModel.SBSTRoute"}, "SBSTRouteID": 153293054, "SR_SVC_NUM": "76", "SR_SVC_DIR": "1", "SR_ROUT_SEQ": "44", "SR_BS_CODE": "92249", "SR_EXP_CODE": "", "SR_DISTANCE": "16.1", "SR_FST_WD": "0636", "SR_LST_WD": "2306", "SR_FST_SAT": "0626", "SR_LST_SAT": "2305", "SR_FST_SUN": "0642", "SR_LST_SUN": "2309", "Summary": "SR_SVC_NUM: 76 SR_SVC_DIR: 1 SR_BS_CODE: 92249 ", "CreateDate": "\/Date(1428320011020)\/"}, {"__metadata": {"uri": "http://datamall.mytransport.sg/LTAoDataService.svc/SBSTRouteSet(153293055)", "type": "LTAModel.SBSTRoute"}, "SBSTRouteID": 153293055, "SR_SVC_NUM": "76", "SR_SVC_DIR": "1", "SR_ROUT_SEQ": "45", "SR_BS_CODE": "92041", "SR_EXP_CODE": "", "SR_DISTANCE": "16.7", "SR_FST_WD": "0638", "SR_LST_WD": "2308", "SR_FST_SAT": "0628", "SR_LST_SAT": "2307", "SR_FST_SUN": "0644", "SR_LST_SUN": "2311", "Summary": "SR_SVC_NUM: 76 SR_SVC_DIR: 1 SR_BS_CODE: 92041 ", "CreateDate": "\/Date(1428320011027)\/"}, {"__metadata": {"uri": "http://datamall.mytransport.sg/LTAoDataService.svc/SBSTRouteSet(153293056)", "type": "LTAModel.SBSTRoute"}, "SBSTRouteID": 153293056, "SR_SVC_NUM": "76", "SR_SVC_DIR": "1", "SR_ROUT_SEQ": "46", "SR_BS_CODE": "92051", "SR_EXP_CODE": "", "SR_DISTANCE": "17.1", "SR_FST_WD": "0640", "SR_LST_WD": "2309", "SR_FST_SAT": "0629", "SR_LST_SAT": "2308", "SR_FST_SUN": "0645", "SR_LST_SUN": "2312", "Summary": "SR_SVC_NUM: 76 SR_SVC_DIR: 1 SR_BS_CODE: 92051 ", "CreateDate": "\/Date(1428320011030)\/"}, {"__metadata": {"uri": "http://datamall.mytransport.sg/LTAoDataService.svc/SBSTRouteSet(153293057)", "type": "LTAModel.SBSTRoute"}, "SBSTRouteID": 153293057, "SR_SVC_NUM": "76", "SR_SVC_DIR": "1", "SR_ROUT_SEQ": "47", "SR_BS_CODE": "92061", "SR_EXP_CODE": "", "SR_DISTANCE": "17.5", "SR_FST_WD": "0642", "SR_LST_WD": "2311", "SR_FST_SAT": "0631", "SR_LST_SAT": "2310", "SR_FST_SUN": "0647", "SR_LST_SUN": "2314", "Summary": "SR_SVC_NUM: 76 SR_SVC_DIR: 1 SR_BS_CODE: 92061 ", "CreateDate": "\/Date(1428320011037)\/"}, {"__metadata": {"uri": "http://datamall.mytransport.sg/LTAoDataService.svc/SBSTRouteSet(153293058)", "type": "LTAModel.SBSTRoute"}, "SBSTRouteID": 153293058, "SR_SVC_NUM": "76", "SR_SVC_DIR": "1", "SR_ROUT_SEQ": "48", "SR_BS_CODE": "92239", "SR_EXP_CODE": "", "SR_DISTANCE": "17.9", "SR_FST_WD": "0644", "SR_LST_WD": "2312", "SR_FST_SAT": "0633", "SR_LST_SAT": "2312", "SR_FST_SUN": "0649", "SR_LST_SUN": "2316", "Summary": "SR_SVC_NUM: 76 SR_SVC_DIR: 1 SR_BS_CODE: 92239 ", "CreateDate": "\/Date(1428320011043)\/"}, {"__metadata": {"uri": "http://datamall.mytransport.sg/LTAoDataService.svc/SBSTRouteSet(153293059)", "type": "LTAModel.SBSTRoute"}, "SBSTRouteID": 153293059, "SR_SVC_NUM": "76", "SR_SVC_DIR": "1", "SR_ROUT_SEQ": "49", "SR_BS_CODE": "92229", "SR_EXP_CODE": "", "SR_DISTANCE": "18.4", "SR_FST_WD": "0647", "SR_LST_WD": "2314", "SR_FST_SAT": "0636", "SR_LST_SAT": "2314", "SR_FST_SUN": "0651", "SR_LST_SUN": "2318", "Summary": "SR_SVC_NUM: 76 SR_SVC_DIR: 1 SR_BS_CODE: 92229 ", "CreateDate": "\/Date(1428320011050)\/"}, {"__metadata": {"uri": "http://datamall.mytransport.sg/LTAoDataService.svc/SBSTRouteSet(153293060)", "type": "LTAModel.SBSTRoute"}, "SBSTRouteID": 153293060, "SR_SVC_NUM": "76", "SR_SVC_DIR": "1", "SR_ROUT_SEQ": "50", "SR_BS_CODE": "92219", "SR_EXP_CODE": "", "SR_DISTANCE": "18.7", "SR_FST_WD": "0545", "SR_LST_WD": "2315", "SR_FST_SAT": "0545", "SR_LST_SAT": "2315", "SR_FST_SUN": "0545", "SR_LST_SUN": "2319", "Summary": "SR_SVC_NUM: 76 SR_SVC_DIR: 1 SR_BS_CODE: 92219 ", "CreateDate": "\/Date(1428320011053)\/"}, {"__metadata": {"uri": "http://datamall.mytransport.sg/LTAoDataService.svc/SBSTRouteSet(153293061)", "type": "LTAModel.SBSTRoute"}, "SBSTRouteID": 153293061, "SR_SVC_NUM": "76", "SR_SVC_DIR": "1", "SR_ROUT_SEQ": "51", "SR_BS_CODE": "92079", "SR_EXP_CODE": "", "SR_DISTANCE": "19.0", "SR_FST_WD": "0546", "SR_LST_WD": "2316", "SR_FST_SAT": "0546", "SR_LST_SAT": "2316", "SR_FST_SUN": "0546", "SR_LST_SUN": "2320", "Summary": "SR_SVC_NUM: 76 SR_SVC_DIR: 1 SR_BS_CODE: 92079 ", "CreateDate": "\/Date(1428320011063)\/"}, {"__metadata": {"uri": "http://datamall.mytransport.sg/LTAoDataService.svc/SBSTRouteSet(153293062)", "type": "LTAModel.SBSTRoute"}, "SBSTRouteID": 153293062, "SR_SVC_NUM": "76", "SR_SVC_DIR": "1", "SR_ROUT_SEQ": "52", "SR_BS_CODE": "92069", "SR_EXP_CODE": "", "SR_DISTANCE": "19.5", "SR_FST_WD": "0549", "SR_LST_WD": "2317", "SR_FST_SAT": "0548", "SR_LST_SAT": "2318", "SR_FST_SUN": "0548", "SR_LST_SUN": "2322", "Summary": "SR_SVC_NUM: 76 SR_SVC_DIR: 1 SR_BS_CODE: 92069 ", "CreateDate": "\/Date(1428320011070)\/"}, {"__metadata": {"uri": "http://datamall.mytransport.sg/LTAoDataService.svc/SBSTRouteSet(153293063)", "type": "LTAModel.SBSTRoute"}, "SBSTRouteID": 153293063, "SR_SVC_NUM": "76", "SR_SVC_DIR": "1", "SR_ROUT_SEQ": "53", "SR_BS_CODE": "92059", "SR_EXP_CODE": "", "SR_DISTANCE": "19.9", "SR_FST_WD": "0549", "SR_LST_WD": "2318", "SR_FST_SAT": "0550", "SR_LST_SAT": "2320", "SR_FST_SUN": "0549", "SR_LST_SUN": "2323", "Summary": "SR_SVC_NUM: 76 SR_SVC_DIR: 1 SR_BS_CODE: 92059 ", "CreateDate": "\/Date(1428320011077)\/"}, {"__metadata": {"uri": "http://datamall.mytransport.sg/LTAoDataService.svc/SBSTRouteSet(153293064)", "type": "LTAModel.SBSTRoute"}, "SBSTRouteID": 153293064, "SR_SVC_NUM": "76", "SR_SVC_DIR": "1", "SR_ROUT_SEQ": "54", "SR_BS_CODE": "92049", "SR_EXP_CODE": "", "SR_DISTANCE": "20.2", "SR_FST_WD": "0550", "SR_LST_WD": "2319", "SR_FST_SAT": "0551", "SR_LST_SAT": "2321", "SR_FST_SUN": "0550", "SR_LST_SUN": "2324", "Summary": "SR_SVC_NUM: 76 SR_SVC_DIR: 1 SR_BS_CODE: 92049 ", "CreateDate": "\/Date(1428320011080)\/"}, {"__metadata": {"uri": "http://datamall.mytransport.sg/LTAoDataService.svc/SBSTRouteSet(153293065)", "type": "LTAModel.SBSTRoute"}, "SBSTRouteID": 153293065, "SR_SVC_NUM": "76", "SR_SVC_DIR": "1", "SR_ROUT_SEQ": "55", "SR_BS_CODE": "92241", "SR_EXP_CODE": "", "SR_DISTANCE": "21.0", "SR_FST_WD": "0553", "SR_LST_WD": "2321", "SR_FST_SAT": "0553", "SR_LST_SAT": "2324", "SR_FST_SUN": "0552", "SR_LST_SUN": "2326", "Summary": "SR_SVC_NUM: 76 SR_SVC_DIR: 1 SR_BS_CODE: 92241 ", "CreateDate": "\/Date(1428320011087)\/"}, {"__metadata": {"uri": "http://datamall.mytransport.sg/LTAoDataService.svc/SBSTRouteSet(153293066)", "type": "LTAModel.SBSTRoute"}, "SBSTRouteID": 153293066, "SR_SVC_NUM": "76", "SR_SVC_DIR": "1", "SR_ROUT_SEQ": "56", "SR_BS_CODE": "92161", "SR_EXP_CODE": "", "SR_DISTANCE": "21.8", "SR_FST_WD": "0555", "SR_LST_WD": "2324", "SR_FST_SAT": "0556", "SR_LST_SAT": "2326", "SR_FST_SUN": "0553", "SR_LST_SUN": "2327", "Summary": "SR_SVC_NUM: 76 SR_SVC_DIR: 1 SR_BS_CODE: 92161 ", "CreateDate": "\/Date(1428320011093)\/"}, {"__metadata": {"uri": "http://datamall.mytransport.sg/LTAoDataService.svc/SBSTRouteSet(153293067)", "type": "LTAModel.SBSTRoute"}, "SBSTRouteID": 153293067, "SR_SVC_NUM": "76", "SR_SVC_DIR": "1", "SR_ROUT_SEQ": "57", "SR_BS_CODE": "82071", "SR_EXP_CODE": "", "SR_DISTANCE": "22.2", "SR_FST_WD": "0557", "SR_LST_WD": "2325", "SR_FST_SAT": "0557", "SR_LST_SAT": "2328", "SR_FST_SUN": "0554", "SR_LST_SUN": "2328", "Summary": "SR_SVC_NUM: 76 SR_SVC_DIR: 1 SR_BS_CODE: 82071 ", "CreateDate": "\/Date(1428320011100)\/"}, {"__metadata": {"uri": "http://datamall.mytransport.sg/LTAoDataService.svc/SBSTRouteSet(153293068)", "type": "LTAModel.SBSTRoute"}, "SBSTRouteID": 153293068, "SR_SVC_NUM": "76", "SR_SVC_DIR": "1", "SR_ROUT_SEQ": "58", "SR_BS_CODE": "82081", "SR_EXP_CODE": "", "SR_DISTANCE": "22.6", "SR_FST_WD": "0558", "SR_LST_WD": "2327", "SR_FST_SAT": "0559", "SR_LST_SAT": "2329", "SR_FST_SUN": "0555", "SR_LST_SUN": "2329", "Summary": "SR_SVC_NUM: 76 SR_SVC_DIR: 1 SR_BS_CODE: 82081 ", "CreateDate": "\/Date(1428320011103)\/"}, {"__metadata": {"uri": "http://datamall.mytransport.sg/LTAoDataService.svc/SBSTRouteSet(153293069)", "type": "LTAModel.SBSTRoute"}, "SBSTRouteID": 153293069, "SR_SVC_NUM": "76", "SR_SVC_DIR": "1", "SR_ROUT_SEQ": "59", "SR_BS_CODE": "82091", "SR_EXP_CODE": "", "SR_DISTANCE": "22.8", "SR_FST_WD": "0559", "SR_LST_WD": "2327", "SR_FST_SAT": "0559", "SR_LST_SAT": "2330", "SR_FST_SUN": "0556", "SR_LST_SUN": "2330", "Summary": "SR_SVC_NUM: 76 SR_SVC_DIR: 1 SR_BS_CODE: 82091 ", "CreateDate": "\/Date(1428320011110)\/"}]}